cmeuncerpy/.DS_Store
cmeuncerpy/__init__.py
cmeuncerpy/_core.abi3.so
cmeuncerpy/_core.pyi
cmeuncerpy/models/LinearRegression.py
cmeuncerpy/models/NeuralNetworkRegression.py
cmeuncerpy/models/__init__.py
cmeuncerpy/py.typed
cmeuncerpy-0.1.43.dist-info/METADATA
cmeuncerpy-0.1.43.dist-info/WHEEL
cmeuncerpy-0.1.43.dist-info/licenses/LICENSE
cmeuncerpy-0.1.43.dist-info/RECORD
