Metadata-Version: 2.4
Name: cmeuncerpy
Version: 0.1.43
Classifier: Development Status :: 3 - Alpha
Classifier: Intended Audience :: Developers
Classifier: Intended Audience :: Science/Research
Classifier: License :: OSI Approved :: MIT License
Classifier: Programming Language :: Python :: 3
Classifier: Programming Language :: Python :: 3.9
Classifier: Programming Language :: Python :: 3.10
Classifier: Programming Language :: Python :: 3.11
Classifier: Programming Language :: Python :: 3.12
Classifier: Programming Language :: Python :: 3.13
Classifier: Programming Language :: Rust
Classifier: Topic :: Scientific/Engineering :: Artificial Intelligence
Requires-Dist: matplotlib>=3.8.0
Requires-Dist: numpy>=1.20.0
Requires-Dist: pandas>=1.3.0
Requires-Dist: scikit-learn>=1.0.0
Requires-Dist: seaborn>=0.11.0
Requires-Dist: torch>=2.0.0
License-File: LICENSE
Summary: Machine learning models implemented in PyTorch and Rust, including Linear Regression and Neural Networks
Keywords: machine-learning,pytorch,regression,neural-networks
Author-email: SyedRaza20 <alizeejah972@gmail.com>
License: MIT
Requires-Python: >=3.9
